ensembl_variant_lookup/__init__.py
ensembl_variant_lookup/api/gene_info.py
ensembl_variant_lookup/api/variant_lookup.py
ensembl_variant_lookup/api/visualization.py
ensembl_variant_lookup/archive/fetch_variants_old.py
ensembl_variant_lookup/archive/forms.py
ensembl_variant_lookup/archive/weather_app.py
ensembl_variant_lookup/fetch_variants.py
ensembl_variant_lookup/images/home.png
ensembl_variant_lookup/images/single_variant_lookup.png
ensembl_variant_lookup/js/scripts.js
ensembl_variant_lookup/static/style.css
ensembl_variant_lookup/static/style_batch_results.css
ensembl_variant_lookup/static/style_index.css
ensembl_variant_lookup/static/style_region_results.css
ensembl_variant_lookup/static/variants_results.css
ensembl_variant_lookup/templates/batch_results.html
ensembl_variant_lookup/templates/index.html
ensembl_variant_lookup/templates/region_results.html
ensembl_variant_lookup/templates/variant_results.html
ensembl_variant_lookup/utils/gene_helpers.py
ensembl_variant_lookup/utils/variant_helpers.py
ensembl_variant_lookup-0.1.2.dist-info/METADATA
ensembl_variant_lookup-0.1.2.dist-info/WHEEL
ensembl_variant_lookup-0.1.2.dist-info/RECORD
