Metadata-Version: 2.1
Name: ensembl-variant-lookup
Version: 0.1.2
Summary: a user-friendly interface for searching individual variants, batch queries, and exploring gene regions from the Ensembl database.
Home-page: https://github.com/danymukesha/ensembl-variant-lookup
Keywords: api,variant,genomics-data,ensembl-rest,danymukesha
Author: Dany Mukesha
Author-email: danymukesha@gmail.com
Requires-Python: >=3.11,<4.0
Classifier: Programming Language :: Python :: 3
Classifier: Programming Language :: Python :: 3.11
Requires-Dist: flask (>=2.0,<3.0)
Requires-Dist: requests (>=2.26,<3.0)
